nolita/__init__.py
nolita/_base_client.py
nolita/_client.py
nolita/_compat.py
nolita/_constants.py
nolita/_exceptions.py
nolita/_files.py
nolita/_models.py
nolita/_qs.py
nolita/_resource.py
nolita/_response.py
nolita/_streaming.py
nolita/_types.py
nolita/_version.py
nolita/py.typed
nolita/_utils/__init__.py
nolita/_utils/_logs.py
nolita/_utils/_proxy.py
nolita/_utils/_reflection.py
nolita/_utils/_streams.py
nolita/_utils/_sync.py
nolita/_utils/_transform.py
nolita/_utils/_typing.py
nolita/_utils/_utils.py
nolita/lib/.keep
nolita/resources/__init__.py
nolita/resources/browse.py
nolita/resources/browser/__init__.py
nolita/resources/browser/browser.py
nolita/resources/browser/session.py
nolita/resources/browser_session/__init__.py
nolita/resources/browser_session/browser_session.py
nolita/resources/browser_session/page.py
nolita/resources/browser_sessions/__init__.py
nolita/resources/browser_sessions/browser_sessions.py
nolita/resources/browser_sessions/pages/__init__.py
nolita/resources/browser_sessions/pages/contents.py
nolita/resources/browser_sessions/pages/pages.py
nolita/resources/browser_sessions/pages/screenshots.py
nolita/types/__init__.py
nolita/types/browse_create_params.py
nolita/types/browser_session_close_response.py
nolita/types/objective_complete.py
nolita/types/browser/__init__.py
nolita/types/browser/session_launch_params.py
nolita/types/browser/session_launch_response.py
nolita/types/browser_session/__init__.py
nolita/types/browser_session/page_browse_params.py
nolita/types/browser_session/page_goto_params.py
nolita/types/browser_session/page_goto_response.py
nolita/types/browser_sessions/__init__.py
nolita/types/browser_sessions/page_close_response.py
nolita/types/browser_sessions/page_do_params.py
nolita/types/browser_sessions/page_do_response.py
nolita/types/browser_sessions/page_list_response.py
nolita/types/browser_sessions/page_new_page_response.py
nolita/types/browser_sessions/page_retrieve_response.py
nolita-0.1.0a1.dist-info/METADATA
nolita-0.1.0a1.dist-info/WHEEL
nolita-0.1.0a1.dist-info/licenses/LICENSE
nolita-0.1.0a1.dist-info/RECORD
